cog/__init__.py
cog/_version.py
cog/base_input.py
cog/base_predictor.py
cog/code_xforms.py
cog/config.py
cog/env_property.py
cog/errors.py
cog/files.py
cog/json.py
cog/logging.py
cog/mimetypes_ext.py
cog/mode.py
cog/predictor.py
cog/schema.py
cog/suppress_output.py
cog/types.py
cog/wait.py
cog/command/__init__.py
cog/command/ast_openapi_schema.py
cog/command/call_graph.py
cog/command/migrate_v1_v1fast.py
cog/command/openapi_schema.py
cog/ext/__init__.py
cog/server/__init__.py
cog/server/connection.py
cog/server/errors.py
cog/server/eventtypes.py
cog/server/exceptions.py
cog/server/helpers.py
cog/server/http.py
cog/server/probes.py
cog/server/response_throttler.py
cog/server/runner.py
cog/server/scope.py
cog/server/telemetry.py
cog/server/useragent.py
cog/server/webhook.py
cog/server/worker.py
cog-0.16.11.dist-info/licenses/LICENSE
cog-0.16.11.dist-info/METADATA
cog-0.16.11.dist-info/WHEEL
cog-0.16.11.dist-info/top_level.txt
cog-0.16.11.dist-info/RECORD
