Metadata-Version: 2.4
Name: cog
Version: 0.16.11
Summary: Containers for machine learning
Author-email: Replicate <team@replicate.com>
License: 
Project-URL: Source, https://github.com/replicate/cog
Classifier: Programming Language :: Python :: 3.8
Classifier: Programming Language :: Python :: 3.9
Classifier: Programming Language :: Python :: 3.10
Classifier: Programming Language :: Python :: 3.11
Classifier: Programming Language :: Python :: 3.12
Classifier: Programming Language :: Python :: 3.13
Requires-Python: >=3.8
License-File: LICENSE
Requires-Dist: attrs<24,>=20.1
Requires-Dist: fastapi<0.119.0,>=0.100
Requires-Dist: pydantic<3,>=1.9
Requires-Dist: PyYAML
Requires-Dist: requests<3,>=2
Requires-Dist: structlog<25,>=20
Requires-Dist: typing_extensions>=4.4.0
Requires-Dist: uvicorn[standard]<1,>=0.12
Dynamic: license-file
